soundarya_operations/__init__.py
soundarya_operations/addsub.py
soundarya_operations/div.py
soundarya_operations/exp.py
soundarya_operations/mul.py
soundarya_operations-0.0.1.dist-info/METADATA
soundarya_operations-0.0.1.dist-info/WHEEL
soundarya_operations-0.0.1.dist-info/top_level.txt
soundarya_operations-0.0.1.dist-info/RECORD
