Metadata-Version: 2.1
Name: soundarya_operations
Version: 0.0.1
Summary: A simple python package for basic arithmetic operations
Home-page: https://github.com/yourusername/my_package
Author: Soundarya
Author-email: soundaryar1008@gmail.com
Classifier: Programming Language :: Python :: 3
Classifier: License :: OSI Approved :: MIT License
Classifier: Operating System :: OS Independent
Requires-Python: >=3.6
Requires-Dist: requests
